{
  "targetState": "in_review",
  "title": "NTA Antrag Vorname Nachname",
  "personalData": {
    "vorname": "",
    "name": "",
    "email": "",
    "phone": "+41 79 000 00 00",
    "matrikel": "00-000-000",
    "studiengang": "",
    "semester": "1",
    "antragsart": "studium"
  },
  "attest": {
    "fileName": "ICF_Attest_Beispiel.md",
    "markdownContent": ""
  },
  "consultation": {
    "status": "done",
    "dateIso": "2026-01-01",
    "date": "",
    "slot": "10:00–10:45",
    "location": "NTA-Fachstelle, Rämistrasse 74, 8001 Zürich (Raum 2.14)",
    "advisor": "Dr. Sandra Meier, NTA-Fachstelle UZH"
  },
  "applicationDefinition": {
    "situationDescription": "",
    "duration": "one_semester",
    "scopeSelections": [],
    "lectureMeasures": [],
    "lectureOtherLines": [],
    "assessmentMeasures": [],
    "assessmentOtherLines": []
  },
  "recommendationHtml": "",
  "recommendationText": "",
  "submittedAt": "2026-01-01T12:00:00.000Z"
}
